ml_verbs/__init__.py
ml_verbs/py.typed
ml_verbs/version.py
ml_verbs/protocols/__init__.py
ml_verbs/protocols/generic.py
ml_verbs/protocols/xy.py
ml_verbs-0.0.4.dist-info/LICENSE
ml_verbs-0.0.4.dist-info/METADATA
ml_verbs-0.0.4.dist-info/WHEEL
ml_verbs-0.0.4.dist-info/top_level.txt
ml_verbs-0.0.4.dist-info/RECORD
