Metadata-Version: 2.1
Name: ml-verbs
Version: 0.0.4
Summary: Generic interfaces for machine learning
License: MIT License
Project-URL: github, https://github.com/NowanIlfideme/ml-verbs
Keywords: ml,machine learning
Classifier: Programming Language :: Python :: 3
Classifier: Development Status :: 2 - Pre-Alpha
Classifier: Intended Audience :: Developers
Classifier: License :: OSI Approved :: MIT License
Classifier: Topic :: Software Development
Classifier: Typing :: Typed
Requires-Python: >=3.9
License-File: LICENSE
Requires-Dist: pydantic-cereal
Provides-Extra: dev
Requires-Dist: setuptools >=61.0.0 ; extra == 'dev'
Requires-Dist: setuptools-scm[toml] >=6.2 ; extra == 'dev'
Requires-Dist: wheel >=0.41 ; extra == 'dev'
Requires-Dist: pre-commit ==3.5.0 ; extra == 'dev'
Requires-Dist: ruff ==0.1.7 ; extra == 'dev'
Requires-Dist: black ==23.11.0 ; extra == 'dev'
Requires-Dist: isort ==5.12.0 ; extra == 'dev'
Requires-Dist: mypy ==1.7.1 ; extra == 'dev'
Requires-Dist: pytest ==7.4.3 ; extra == 'dev'
Requires-Dist: pytest-lazy-fixture ==0.6.3 ; extra == 'dev'
Requires-Dist: jupyter ; extra == 'dev'
Requires-Dist: ipykernel ; extra == 'dev'
Requires-Dist: pandas-stubs ; extra == 'dev'
Provides-Extra: dev_extras
Requires-Dist: pandas ; extra == 'dev_extras'
Requires-Dist: polars ; extra == 'dev_extras'
Requires-Dist: xarray ; extra == 'dev_extras'
Requires-Dist: pyspark ; extra == 'dev_extras'
Provides-Extra: docs
Requires-Dist: mkdocs ==1.5.3 ; extra == 'docs'
Requires-Dist: mkdocs-material ==9.5.1 ; extra == 'docs'
Requires-Dist: mkdocstrings ==0.24.0 ; extra == 'docs'
Requires-Dist: mkdocstrings-python ==1.7.5 ; extra == 'docs'
Requires-Dist: mkdocs-jupyter ==0.24.6 ; extra == 'docs'
Requires-Dist: pygments ==2.17.2 ; extra == 'docs'
